autoprox/__init__.py
autoprox/main.py
autoprox/run.py
autoprox-0.1.0.dist-info/METADATA
autoprox-0.1.0.dist-info/WHEEL
autoprox-0.1.0.dist-info/entry_points.txt
autoprox-0.1.0.dist-info/top_level.txt
autoprox-0.1.0.dist-info/RECORD
