Metadata-Version: 2.2
Name: autoprox
Version: 0.1.0
Summary: simple autonomi proxy server written in python
Requires-Python: >=3.11
Requires-Dist: autonomi-client>=0.3.61
Requires-Dist: fastapi>=0.110.0
Requires-Dist: uvicorn>=0.27.1
Requires-Dist: pydantic>=2.6.3
Provides-Extra: dev
Requires-Dist: black>=24.2.0; extra == "dev"
Requires-Dist: mypy>=1.9.0; extra == "dev"
Requires-Dist: ruff>=0.3.0; extra == "dev"
